{
  "basics": {
    "name": "Alex Nascimento",
    "label_pt": "Logística | Transporte e Armazenagem | Ciência de Dados",
    "label_en": "Logistics | Transportation & Storage | Data Science",
    "email": "alex_nascto@hotmail.com",
    "phone": "(19) 98290-7060",
    "location": "Indaiatuba, São Paulo",
    "linkedin": "linkedin.com/in/alexnascimento1980",
    "github": "github.com/SeuUsuario"
  },
  "summary": {
    "pt": [
      "Experiência em agendamento e planejamento estratégico de entregas, garantindo eficiência e pontualidade.",
      "Gestão de frota para abastecimento de estoque, promovendo uma cadeia de suprimentos ininterrupta."
    ],
    "en": [
      "Experience in scheduling and strategic delivery planning, ensuring efficiency and punctuality.",
      "Fleet management for inventory replenishment, promoting an uninterrupted supply chain."
    ]
  },
  "experience": [
    {
      "company": "DHL Supply Chain",
      "startDate": "05/2019",
      "endDate": "09/2024",
      "position_pt": "Assistente de Transporte",
      "position_en": "Transport Assistant",
      "highlights_pt": [
        "Trabalho focado em atendimento a coletas de produtos comercializados via aplicativo de venda (Primeira Milha do cliente).",
        "Treinamento dos motoristas terceiros para atendimento com excelência e padrão acertados com cliente.",
        "Gestão da base de motoristas parceiros para manutenção do interesse e disponibilidade na operação."
      ],
      "highlights_en": [
        "Focused on product collection services sold via sales application (Customer's First Mile).",
        "Trained third-party drivers to provide excellent service according to client standards.",
        "Managed the partner driver base to maintain interest and operational availability."
      ]
    },
    {
      "company": "West Side Viagens E Turismo (Grupo Belarmino)",
      "startDate": "07/2018",
      "endDate": "05/2019",
      "position_pt": "Auxiliar de Tráfego",
      "position_en": "Traffic Assistant",
      "highlights_pt": [
        "Controle de escala e cumprimento de horário de início de jornada de motoristas das linhas de fretamento.",
        "Controle e arquivamento dos discos de tacógrafo e diários de bordo de cada um dos veículos da frota."
      ],
      "highlights_en": [
        "Controlled schedules and ensured adherence to shift start times for charter line drivers.",
        "Managed and archived tachograph discs and logbooks for all fleet vehicles."
      ]
    }
  ],
  "education": [
    {
      "institution": "UNIVESP",
      "startDate": "2024",
      "endDate": "Present",
      "area_pt": "Bacharel em Ciência de Dados",
      "area_en": "Bachelor's in Data Science",
      "status_pt": "Cursando o 4º semestre",
      "status_en": "4th semester ongoing"
    }
  ],
  "skills": {
    "technical": ["Python", "SQL", "Power BI", "Pacote Office", "ERP (TMS e SAP)"],
    "languages": [
      {
        "language_pt": "Inglês",
        "language_en": "English",
        "fluency_pt": "Iniciante",
        "fluency_en": "Beginner"
      }
    ]
  }
}